ctlib_webstack/__init__.py
ctlib_webstack/fastapi/README.md
ctlib_webstack/fastapi/__init__.py
ctlib_webstack/fastapi/error_handler/README.md
ctlib_webstack/fastapi/error_handler/__init__.py
ctlib_webstack/fastapi/error_handler/handler.py
ctlib_webstack/fastapi/error_handler/wrapper.py
ctlib_webstack/fastapi/ip_filter/README.md
ctlib_webstack/fastapi/ip_filter/__init__.py
ctlib_webstack/fastapi/ip_filter/ip_filter.py
ctlib_webstack-0.1.3.dist-info/METADATA
ctlib_webstack-0.1.3.dist-info/WHEEL
ctlib_webstack-0.1.3.dist-info/RECORD
