Metadata-Version: 2.4
Name: ctlib-webstack
Version: 0.1.3
Summary: A collection of common web middlewares for security and request processing.
Project-URL: Homepage, https://git.codetech.top/ctlib/ctlib-webstack
Project-URL: Repository, https://git.codetech.top/ctlib/ctlib-webstack
Author-email: Jimin <jimin@codetech.top>
License: MIT
Classifier: Framework :: AsyncIO
Classifier: License :: OSI Approved :: MIT License
Classifier: Operating System :: OS Independent
Classifier: Programming Language :: Python :: 3
Classifier: Programming Language :: Python :: 3 :: Only
Requires-Python: >=3.8
Requires-Dist: ctlib-geoip>=0.1.1
Requires-Dist: starlette>=0.27
Provides-Extra: fastapi
Requires-Dist: fastapi>=0.103; extra == 'fastapi'
Requires-Dist: pydantic>=2; extra == 'fastapi'
